<?xml version="1.0" encoding="utf-8"?>
<extension version="1.6" type="plugin" group="content">
	<name>Content - QTube</name>
	<author>Massimo Giagnoni</author>
	<authorUrl>http://www.latenight-coding.com</authorUrl>
	<creationDate>March 2008</creationDate>
	<copyright>Copyright (C) 2008 Massimo Giagnoni. All rights reserved.</copyright>
	<license>http://www.gnu.org/copyleft/gpl.html GNU/GPL</license>
	<version>1.0.0</version>
	<description>Insert YouTube hosted videos in Joomla! contents. Do not forget to go to Plugin Manager and publish the plugin. Online help at http://www.latenight-coding.com/joomla-addons/qtube.html
	
	Syntax: {qtube vid:=xxx}
	or:	{qtube vid:=xxx w:=320 h:=267 c1:=00ff00 c2:=0000ff b:=1 rel:=1 ap:=1 cl:=class id:=id}</description>
	<files>
		<filename plugin="qtube">qtube.php</filename>
	</files>
	<config>
		 <fields name="params">
		 	<fieldset name="basic">
				<field name="class" type="text" default="" size="15" label="Container class" description="&lt;i&gt;(Advanced)&lt;/i&gt;&lt;br /&gt;&lt;i&gt;qtube tag:&lt;/i&gt; cl&lt;br /&gt;&lt;br /&gt; CSS Class to use" />
				<field name="id" type="text" default="" size="15" label="Container Id" description="&lt;i&gt;(Advanced)&lt;/i&gt;&lt;br /&gt;&lt;i&gt;qtube tag:&lt;/i&gt; id&lt;br /&gt;&lt;br /&gt; CSS Id to use" />
				<field name="width" type="text" default="425" size="5" label="Width" description="&lt;i&gt;qtube tag:&lt;/i&gt; w&lt;br /&gt;&lt;br /&gt;Video Frame Width in Pixels" />
				<field name="height" type="text" default="355" size="5" label="Height" description="&lt;i&gt;qtube tag:&lt;/i&gt; h&lt;br /&gt;&lt;br /&gt;Video Frame Height in Pixels" />
				<field name="related" type="list" default="1" label="Related videos" description="&lt;i&gt;qtube tag:&lt;/i&gt; rel&lt;br /&gt;&lt;br /&gt;Links to related videos are displayed once video has finished to play">
		            <option value="0">No</option>
		            <option value="1">Yes</option>
				</field>
				<field name="color1" type="text" default="" size="5" label="Color1" description="&lt;i&gt;qtube tag:&lt;/i&gt; c1&lt;br /&gt;&lt;br /&gt;Color to format the video player button bar. Use hexadecimal values.&lt;br /&gt;&lt;br /&gt;&lt;i&gt;Example:&lt;/i&gt; b1b1b1" />
				<field name="color2" type="text" default="" size="5" label="Color2" description="&lt;i&gt;qtube tag:&lt;/i&gt; c2&lt;br /&gt;&lt;br /&gt;Color to format the video player button bar. Use hexadecimal values.&lt;br /&gt;&lt;br /&gt;&lt;i&gt;Example:&lt;/i&gt; cfcfcf" />
				<field name="border" type="list" default="0" label="Border" description="&lt;i&gt;qtube tag:&lt;/i&gt; b&lt;br /&gt;&lt;br /&gt;Draw a border around video player frame">
		            <option value="0">No</option>
		            <option value="1">Yes</option>
				</field>
				<field name="autoplay" type="list" default="0" label="Autoplay" description="&lt;i&gt;qtube tag:&lt;/i&gt; ap&lt;br /&gt;&lt;br /&gt;Play the video as soon as the page is loaded, user do not need to start it manually with the 'play' button">
		            <option value="0">No</option>
		            <option value="1">Yes</option>
				</field>
			</fieldset>
		</fields>  
	</config>
</extension>